pyeapi/__init__.py
pyeapi/client.py
pyeapi/eapilib.py
pyeapi/utils.py
pyeapi/api/__init__.py
pyeapi/api/abstract.py
pyeapi/api/acl.py
pyeapi/api/bgp.py
pyeapi/api/interfaces.py
pyeapi/api/ipinterfaces.py
pyeapi/api/mlag.py
pyeapi/api/ntp.py
pyeapi/api/ospf.py
pyeapi/api/routemaps.py
pyeapi/api/spanningtree.py
pyeapi/api/staticroute.py
pyeapi/api/stp.py
pyeapi/api/switchports.py
pyeapi/api/system.py
pyeapi/api/users.py
pyeapi/api/varp.py
pyeapi/api/vlans.py
pyeapi/api/vrfs.py
pyeapi/api/vrrp.py
pyeapi_fork-0.8.4rc3.dist-info/LICENSE
pyeapi_fork-0.8.4rc3.dist-info/METADATA
pyeapi_fork-0.8.4rc3.dist-info/WHEEL
pyeapi_fork-0.8.4rc3.dist-info/top_level.txt
pyeapi_fork-0.8.4rc3.dist-info/RECORD
